Metadata-Version: 2.1
Name: django-tagging-autocomplete-new
Version: 0.6.3
Summary: Autocompletion for django-tagging. Rebuild for Django 2.2. Original by Ludwik Trammer.
Home-page: https://github.com/GrobIvanovich/django-tagging-autocomplete-new/
Author: GrobIvanovich
Author-email: killmaster00431@gmail.com
License: MIT
Keywords: Django,Tags autocompletion
Platform: UNKNOWN
Classifier: Development Status :: 4 - Beta
Classifier: Environment :: Web Environment
Classifier: Intended Audience :: Developers
Classifier: License :: OSI Approved :: MIT License
Classifier: Operating System :: OS Independent
Classifier: Programming Language :: Python
Classifier: Programming Language :: Python :: 3
Classifier: Framework :: Django :: 2.2
Classifier: Topic :: Software Development :: Libraries :: Python Modules
